npfl138/LICENSE
npfl138/README.md
npfl138/__init__.py
npfl138/first_time.py
npfl138/initializers_override.py
npfl138/metrics.py
npfl138/rl_utils.py
npfl138/startup.py
npfl138/trainable_module.py
npfl138/transformed_dataset.py
npfl138/version.py
npfl138/vocabulary.py
npfl138/datasets/__init__.py
npfl138/datasets/cags.py
npfl138/datasets/cifar10.py
npfl138/datasets/common_voice_cs.py
npfl138/datasets/gym_cartpole_dataset.py
npfl138/datasets/homr_dataset.py
npfl138/datasets/image64_dataset.py
npfl138/datasets/mnist.py
npfl138/datasets/modelnet.py
npfl138/datasets/morpho_analyzer.py
npfl138/datasets/morpho_dataset.py
npfl138/datasets/reading_comprehension_dataset.py
npfl138/datasets/svhn.py
npfl138/datasets/text_classification_dataset.py
npfl138/datasets/tfrecord_dataset.py
npfl138/datasets/tts_dataset.py
npfl138/datasets/uppercase_data.py
npfl138/envs/__init__.py
npfl138/envs/cart_pole_pixels.py
npfl138/envs/cart_pole_pixels_interactive.py
npfl138-2425.14.3.dist-info/licenses/npfl138/LICENSE
npfl138-2425.14.3.dist-info/METADATA
npfl138-2425.14.3.dist-info/WHEEL
npfl138-2425.14.3.dist-info/top_level.txt
npfl138-2425.14.3.dist-info/RECORD
