Metadata-Version: 2.4
Name: npfl138
Version: 2425.14.3
Summary: Modules used by the Deep Learning Course NPFL138
Author-email: Milan Straka <straka@ufal.mff.cuni.cz>
License: MPL-2.0
Project-URL: Homepage, https://ufal.mff.cuni.cz/courses/npfl138
Project-URL: Repository, https://github.com/ufal/npfl138
Classifier: License :: OSI Approved :: Mozilla Public License 2.0 (MPL 2.0)
Classifier: Programming Language :: Python :: 3
Requires-Python: >=3.10
License-File: npfl138/LICENSE
Requires-Dist: torch~=2.6.0
Requires-Dist: torchaudio~=2.6.0
Requires-Dist: torchvision~=0.21.0
Requires-Dist: torchmetrics~=1.6.1
Requires-Dist: timm~=1.0.14
Requires-Dist: transformers~=4.49.0
Requires-Dist: flashlight-text~=0.0.7
Requires-Dist: soundfile~=0.13.1
Requires-Dist: gymnasium~=1.1.1
Requires-Dist: pygame~=2.6.1
Requires-Dist: matplotlib~=3.10.1
Requires-Dist: tensorboard~=2.18.0
Requires-Dist: standard-imghdr; python_version >= "3.13"
Dynamic: license-file
